django_saml2_auth_multi/__init__.py
django_saml2_auth_multi/config.py
django_saml2_auth_multi/errors.py
django_saml2_auth_multi/exceptions.py
django_saml2_auth_multi/saml.py
django_saml2_auth_multi/templates/django_saml2_auth_multi/denied.html
django_saml2_auth_multi/templates/django_saml2_auth_multi/error.html
django_saml2_auth_multi/templates/django_saml2_auth_multi/signout.html
django_saml2_auth_multi/tests/__init__.py
django_saml2_auth_multi/tests/conftest.py
django_saml2_auth_multi/tests/metadata.xml
django_saml2_auth_multi/tests/settings.py
django_saml2_auth_multi/tests/test_saml.py
django_saml2_auth_multi/tests/test_user.py
django_saml2_auth_multi/tests/test_utils.py
django_saml2_auth_multi/tests/utils.py
django_saml2_auth_multi/urls.py
django_saml2_auth_multi/user.py
django_saml2_auth_multi/utils.py
django_saml2_auth_multi/views.py
django_saml2_auth_multi-3.11.3.dist-info/AUTHORS.md
django_saml2_auth_multi-3.11.3.dist-info/LICENSE
django_saml2_auth_multi-3.11.3.dist-info/METADATA
django_saml2_auth_multi-3.11.3.dist-info/WHEEL
django_saml2_auth_multi-3.11.3.dist-info/RECORD
