Metadata-Version: 2.1
Name: django_saml2_auth_multi
Version: 3.11.3
Summary: Django SAML2 Authentication For Multi IdP Setups Made Easy.
Home-page: https://github.com/mfnd/django-saml2-auth-multi
License: Apache 2.0
Keywords: django,saml,saml2sso,authentication,okta,standard
Author: Fang Li
Author-email: surivlee+djsaml2auth@gmail.com
Classifier: Development Status :: 5 - Production/Stable
Classifier: Framework :: Django :: 2.2
Classifier: Framework :: Django :: 3.2
Classifier: Framework :: Django :: 4.0
Classifier: Framework :: Django :: 4.1
Classifier: Intended Audience :: Developers
Classifier: License :: OSI Approved :: Apache Software License
Classifier: License :: Other/Proprietary License
Classifier: Programming Language :: Python :: 2
Classifier: Programming Language :: Python :: 2.7
Classifier: Programming Language :: Python :: 3
Classifier: Programming Language :: Python :: 3.4
Classifier: Programming Language :: Python :: 3.5
Classifier: Programming Language :: Python :: 3.6
Classifier: Programming Language :: Python :: 3.7
Classifier: Programming Language :: Python :: 3.8
Classifier: Programming Language :: Python :: 3.9
Classifier: Programming Language :: Python :: 3.10
Classifier: Programming Language :: Python :: 3.11
Classifier: Programming Language :: Python :: 3.12
Classifier: Programming Language :: Python :: 3.13
Classifier: Topic :: Software Development :: Libraries :: Python Modules
Requires-Dist: dictor (==0.1.11)
Requires-Dist: pyjwt (==2.9.0)
Requires-Dist: pysaml2 (==7.4.2)
Requires-Dist: setuptools (>=67.8.0)
